COPYING
MANIFEST.in
README.html
README.rst
crcgen
crcgen_test.py
setup.py
crcgen.egg-info/PKG-INFO
crcgen.egg-info/SOURCES.txt
crcgen.egg-info/dependency_links.txt
crcgen.egg-info/top_level.txt
libcrcgen/__init__.py
libcrcgen/__main__.py
libcrcgen/generator.py
libcrcgen/generator_test.py
libcrcgen/main.py
libcrcgen/parameters.py
libcrcgen/reference.py
libcrcgen/util.py
libcrcgen/version.py