Metadata-Version: 2.1
Name: crcgen
Version: 2.5
Summary: CRC algorithm HDL code generator (VHDL, Verilog, MyHDL)
Home-page: https://bues.ch/h/crcgen
Author: Michael Büsch
Author-email: m@bues.ch
License: GNU General Public License v2 or later
Keywords: CRC Verilog VHDL MyHDL FPGA codegenerator
Classifier: Development Status :: 5 - Production/Stable
Classifier: Environment :: Console
Classifier: Intended Audience :: Developers
Classifier: Intended Audience :: Education
Classifier: Intended Audience :: Information Technology
Classifier: Intended Audience :: Science/Research
Classifier: Intended Audience :: Telecommunications Industry
Classifier: License :: OSI Approved :: GNU General Public License v2 or later (GPLv2+)
Classifier: License :: Public Domain
Classifier: Operating System :: OS Independent
Classifier: Programming Language :: Python
Classifier: Programming Language :: Python :: 3
Classifier: Topic :: Education
Classifier: Topic :: Scientific/Engineering
Classifier: Topic :: Software Development
Classifier: Topic :: Software Development :: Code Generators
Classifier: Topic :: Utilities
Requires-Python: >=3.7
License-File: COPYING
